kanji_lists/__init__.py
kanji_lists/kanji_lists.py
kanji_lists-0.1.0.dist-info/LICENSE
kanji_lists-0.1.0.dist-info/WHEEL
kanji_lists-0.1.0.dist-info/METADATA
kanji_lists-0.1.0.dist-info/RECORD
