Metadata-Version: 2.1
Name: kanji-lists
Version: 0.1.0
Summary: Collection of Japanese kanji lists
Home-page: https://github.com/ffe4/kanji-lists
License: MIT
Keywords: japanese,kanji
Author: Daniel Lemm
Author-email: daniel.lemm@outlook.com
Requires-Python: >=3.6,<4.0
Classifier: Development Status :: 3 - Alpha
Classifier: Intended Audience :: Developers
Classifier: License :: OSI Approved :: MIT License
Classifier: Natural Language :: Japanese
Classifier: Programming Language :: Python :: 3
Classifier: Programming Language :: Python :: 3.6
Classifier: Programming Language :: Python :: 3.7
Classifier: Programming Language :: Python :: 3.8
Classifier: Topic :: Software Development :: Libraries :: Python Modules
Project-URL: Repository, https://github.com/ffe4/kanji-lists
